atlas_cp/__init__.py
atlas_cp/__main__.py
atlas_cp/atlas_cp.py
atlas_cp-1.0.0.dist-info/DESCRIPTION.rst
atlas_cp-1.0.0.dist-info/METADATA
atlas_cp-1.0.0.dist-info/RECORD
atlas_cp-1.0.0.dist-info/WHEEL
atlas_cp-1.0.0.dist-info/entry_points.txt
atlas_cp-1.0.0.dist-info/metadata.json
atlas_cp-1.0.0.dist-info/top_level.txt
