Metadata-Version: 2.0
Name: atlas-cp
Version: 1.0.0
Summary: Quickly add users to ATLAS CP server at Illinois
Home-page: https://git.math.illinois.edu/math-it/atlas-cp
Author: Patrick Szuta
Author-email: szuta@illinois.edu
License: UNKNOWN
Platform: UNKNOWN
Requires-Python: >=3
Requires-Dist: ldap3
Requires-Dist: requests
Requires-Dist: urllib3
